.DS_Store
pytester/__init__.py
pytester/pytester.py
pytester_efficiency-0.2.0.dist-info/LICENSE
pytester_efficiency-0.2.0.dist-info/METADATA
pytester_efficiency-0.2.0.dist-info/WHEEL
pytester_efficiency-0.2.0.dist-info/top_level.txt
pytester_efficiency-0.2.0.dist-info/RECORD
