Metadata-Version: 2.1
Name: pytester-efficiency
Version: 0.2.0
Summary: A package to test python functions
Home-page: https://github.com/TheFiremanH/pytester
Author: Hippolyte Melica
Author-email: hippolytemelica@gmail.com
License: UNKNOWN
Project-URL: Bug Tracker, https://github.com/TheFiremanH/pytester/issues
Platform: UNKNOWN
Classifier: Programming Language :: Python :: 3
Classifier: License :: OSI Approved :: MIT License
Classifier: Operating System :: OS Independent
Requires-Python: >=3.6
